CONTRIBUTING.md
LICENSE.txt
MANIFEST.in
README.md
setup.py
github_trending/__init__.py
github_trending/compat.py
github_trending/completer.py
github_trending/completions.py
github_trending/config.py
github_trending/github.py
github_trending/github_trending.py
github_trending/github_trending_cli.py
github_trending/keys.py
github_trending/main.py
github_trending/main_cli.py
github_trending/style.py
github_trending/toolbar.py
github_trending/utils.py
github_trending/lib/__init__.py
github_trending/lib/github/__init__.py
github_trending/lib/github/github.py
github_trending/lib/mdv/__init__.py
github_trending/lib/mdv/ansi_tables.json
github_trending/lib/mdv/markdownviewer.py
github_trending/lib/mdv/tabulate.py
github_trending_cli.egg-info/PKG-INFO
github_trending_cli.egg-info/SOURCES.txt
github_trending_cli.egg-info/dependency_links.txt
github_trending_cli.egg-info/entry_points.txt
github_trending_cli.egg-info/requires.txt
github_trending_cli.egg-info/top_level.txt