Metadata-Version: 1.1
Name: github-trending-cli
Version: 1.0.1
Summary: View Github Trending and repository README from the command line
Home-page: https://github.com/blue-9/github-trending
Author: Yuya Chiba
Author-email: cy.blue.9@gmail.com
License: Apache License 2.0
Download-URL: https://pypi.python.org/pypi/github-trending-cli
Platform: UNKNOWN
Classifier: Intended Audience :: Developers
Classifier: Intended Audience :: System Administrators
Classifier: License :: OSI Approved :: Apache Software License
Classifier: Natural Language :: English
Classifier: Programming Language :: Python
Classifier: Programming Language :: Python :: 2.6
Classifier: Programming Language :: Python :: 2.7
Classifier: Programming Language :: Python :: 3
Classifier: Programming Language :: Python :: 3.4
Classifier: Programming Language :: Python :: 3.5
Classifier: Topic :: Software Development
Classifier: Topic :: Software Development :: Libraries :: Python Modules
